stream_csv/__init__.py
stream_csv/sqlalchemy.py
stream_csv/stream.py
stream_csv-0.1.1.dist-info/LICENSE
stream_csv-0.1.1.dist-info/WHEEL
stream_csv-0.1.1.dist-info/METADATA
stream_csv-0.1.1.dist-info/RECORD
